alchemyst_ai/__init__.py
alchemyst_ai/_base_client.py
alchemyst_ai/_client.py
alchemyst_ai/_compat.py
alchemyst_ai/_constants.py
alchemyst_ai/_exceptions.py
alchemyst_ai/_files.py
alchemyst_ai/_models.py
alchemyst_ai/_qs.py
alchemyst_ai/_resource.py
alchemyst_ai/_response.py
alchemyst_ai/_streaming.py
alchemyst_ai/_types.py
alchemyst_ai/_version.py
alchemyst_ai/py.typed
alchemyst_ai/_utils/__init__.py
alchemyst_ai/_utils/_compat.py
alchemyst_ai/_utils/_datetime_parse.py
alchemyst_ai/_utils/_logs.py
alchemyst_ai/_utils/_proxy.py
alchemyst_ai/_utils/_reflection.py
alchemyst_ai/_utils/_resources_proxy.py
alchemyst_ai/_utils/_streams.py
alchemyst_ai/_utils/_sync.py
alchemyst_ai/_utils/_transform.py
alchemyst_ai/_utils/_typing.py
alchemyst_ai/_utils/_utils.py
alchemyst_ai/lib/.keep
alchemyst_ai/resources/__init__.py
alchemyst_ai/resources/v1/__init__.py
alchemyst_ai/resources/v1/v1.py
alchemyst_ai/resources/v1/context/__init__.py
alchemyst_ai/resources/v1/context/context.py
alchemyst_ai/resources/v1/context/memory.py
alchemyst_ai/resources/v1/context/traces.py
alchemyst_ai/resources/v1/context/view.py
alchemyst_ai/resources/v1/context/add_async/__init__.py
alchemyst_ai/resources/v1/context/add_async/add_async.py
alchemyst_ai/resources/v1/context/add_async/status.py
alchemyst_ai/resources/v1/org/__init__.py
alchemyst_ai/resources/v1/org/context.py
alchemyst_ai/resources/v1/org/org.py
alchemyst_ai/types/__init__.py
alchemyst_ai/types/v1/__init__.py
alchemyst_ai/types/v1/context_add_params.py
alchemyst_ai/types/v1/context_add_response.py
alchemyst_ai/types/v1/context_delete_params.py
alchemyst_ai/types/v1/context_search_params.py
alchemyst_ai/types/v1/context_search_response.py
alchemyst_ai/types/v1/context/__init__.py
alchemyst_ai/types/v1/context/add_async_cancel_response.py
alchemyst_ai/types/v1/context/add_async_create_params.py
alchemyst_ai/types/v1/context/add_async_create_response.py
alchemyst_ai/types/v1/context/memory_add_params.py
alchemystai-0.10.0.dist-info/METADATA
alchemystai-0.10.0.dist-info/WHEEL
alchemystai-0.10.0.dist-info/licenses/LICENSE
alchemystai-0.10.0.dist-info/RECORD
